mccabe_cli/__init__.py
mccabe_cli-0.1.2.dist-info/entry_points.txt
mccabe_cli-0.1.2.dist-info/WHEEL
mccabe_cli-0.1.2.dist-info/METADATA
mccabe_cli-0.1.2.dist-info/RECORD
