Metadata-Version: 2.1
Name: mccabe-cli
Version: 0.1.2
Summary: 
Home-page: https://github.com/tddschn/mccabe-cli
License: MIT
Keywords: mccabe,code complexity,code metrics
Author: Xinyuan Chen
Author-email: 45612704+tddschn@users.noreply.github.com
Requires-Python: >=3.10,<4.0
Classifier: License :: OSI Approved :: MIT License
Classifier: Programming Language :: Python :: 3
Classifier: Programming Language :: Python :: 3.10
Classifier: Topic :: Utilities
Requires-Dist: mccabe (>=0.7.0,<0.8.0)
Project-URL: Bug Tracker, https://github.com/tddschn/mccabe-cli/issues
Project-URL: Repository, https://github.com/tddschn/mccabe-cli
